restrict/__init__.py
restrict/compiler/__init__.py
restrict/compiler/ast.py
restrict/compiler/compiled.py
restrict/compiler/compiler.py
restrict/compiler/exceptions/__init__.py
restrict/compiler/exceptions/compile.py
restrict/compiler/exceptions/runtime.py
restrict/compiler/lexers.py
restrict/compiler/parsers.py
restrict/compiler/ply/lex.py
restrict/compiler/ply/yacc.py
restrict/compiler/resolver.py
restrict/compiler/transformers.py
restrict/compiler/types.py
restrict/compiler/visitors.py
restrict/compiler/walker_utils.py
restrict/resources/__init__.py
restrict/resources/postgresql.py
restrict/resources/specs.py
restrict/resources/starlette.py
restrict/types/__init__.py
restrict/types/builtins.py
restrict/types/numeric.py
restrict/types/system.py
restrict/types/text.py
restrict/types/time.py
restrict/web/starlette.py
restrict_framework-0.2.1a0.dist-info/LICENSE
restrict_framework-0.2.1a0.dist-info/METADATA
restrict_framework-0.2.1a0.dist-info/WHEEL
restrict_framework-0.2.1a0.dist-info/RECORD
