Metadata-Version: 2.3
Name: restrict-framework
Version: 0.2.1a0
Summary: A functional resource-oriented Web framework
License: MIT
Keywords: rest,hateoas,restrict
Author: Curtis Schlak
Author-email: 696163-realistschuckle@users.noreply.gitlab.com
Requires-Python: >=3.12,<4.0
Classifier: License :: OSI Approved :: MIT License
Classifier: Programming Language :: Python :: 3
Classifier: Programming Language :: Python :: 3.12
Classifier: Programming Language :: Python :: 3.13
Provides-Extra: dev
Provides-Extra: docs
Provides-Extra: starlette
Provides-Extra: test
Requires-Dist: black (>=25.1.0,<26.0.0) ; extra == "dev"
Requires-Dist: isodate (>=0.7.2,<0.8.0)
Requires-Dist: itsdangerous (>=2.2.0,<3.0.0) ; extra == "starlette"
Requires-Dist: jupyter-book (>=1.0.4.post0,<2.0.0) ; extra == "docs"
Requires-Dist: pyclean (>=3.1.0,<4.0.0) ; extra == "dev"
Requires-Dist: pydata-sphinx-theme (>=0.16.1,<0.17.0) ; extra == "docs"
Requires-Dist: pydeps (>=3.0.1,<4.0.0) ; extra == "docs"
Requires-Dist: pygments (>=2.19.1,<3.0.0) ; extra == "docs"
Requires-Dist: pygments-restrict (>=0.1.5,<0.2.0) ; extra == "docs"
Requires-Dist: pynvim (>=0.5.2,<0.6.0) ; extra == "dev"
Requires-Dist: pytest (>=8.3.4,<9.0.0) ; extra == "test"
Requires-Dist: pytest-asyncio (>=0.25.3,<0.26.0) ; extra == "test"
Requires-Dist: pytest-cov (>=6.0.0,<7.0.0) ; extra == "test"
Requires-Dist: pytest-watcher (>=0.4.3,<0.5.0) ; extra == "dev"
Requires-Dist: python-multipart (>=0.0.20,<0.0.21) ; extra == "starlette"
Requires-Dist: starlette (>=0.46.0,<0.47.0) ; extra == "starlette"
Requires-Dist: uvicorn[standard] (>=0.34.0,<0.35.0) ; extra == "dev"
Project-URL: Documentation, https://restrictframework.io
Project-URL: Homepage, https://restrictframework.io
Project-URL: Issues, https://gitlab.com/restrict-framework/restrict.py/-/issues
Project-URL: Repository, https://gitlab.com/restrict-framework/restrict.py
